setup.py
brynq_sdk_factorial/__init__.py
brynq_sdk_factorial/companies.py
brynq_sdk_factorial/compensations.py
brynq_sdk_factorial/contracts.py
brynq_sdk_factorial/costcenter.py
brynq_sdk_factorial/custom_fields.py
brynq_sdk_factorial/employees.py
brynq_sdk_factorial/family_situation.py
brynq_sdk_factorial/files.py
brynq_sdk_factorial/locations.py
brynq_sdk_factorial/payroll.py
brynq_sdk_factorial/teams.py
brynq_sdk_factorial/workschedules.py
brynq_sdk_factorial.egg-info/PKG-INFO
brynq_sdk_factorial.egg-info/SOURCES.txt
brynq_sdk_factorial.egg-info/dependency_links.txt
brynq_sdk_factorial.egg-info/not-zip-safe
brynq_sdk_factorial.egg-info/requires.txt
brynq_sdk_factorial.egg-info/top_level.txt
brynq_sdk_factorial/schemas/attendance_schemas.py
brynq_sdk_factorial/schemas/banking_schemas.py
brynq_sdk_factorial/schemas/companies_schemas.py
brynq_sdk_factorial/schemas/contracts_schemas.py
brynq_sdk_factorial/schemas/documents_schemas.py
brynq_sdk_factorial/schemas/employee_updates_schemas.py
brynq_sdk_factorial/schemas/employees_schemas.py
brynq_sdk_factorial/schemas/expenses_schemas.py
brynq_sdk_factorial/schemas/family_situation.py
brynq_sdk_factorial/schemas/finance_schemas.py
brynq_sdk_factorial/schemas/holidays_schemas.py
brynq_sdk_factorial/schemas/job_catalog_schemas.py
brynq_sdk_factorial/schemas/locations_schemas.py
brynq_sdk_factorial/schemas/payroll_employees_schemas.py
brynq_sdk_factorial/schemas/payroll_integrations_base_schemas.py
brynq_sdk_factorial/schemas/payroll_schemas.py
brynq_sdk_factorial/schemas/project_management_schemas.py
brynq_sdk_factorial/schemas/shift_management_schemas.py
brynq_sdk_factorial/schemas/teams_schemas.py
brynq_sdk_factorial/schemas/time_planning_schemas.py
brynq_sdk_factorial/schemas/time_settings_schemas.py
brynq_sdk_factorial/schemas/timeoff_schemas.py
brynq_sdk_factorial/schemas/trainings_schemas.py
brynq_sdk_factorial/schemas/work_schedule_schemas.py