Metadata-Version: 1.0
Name: brynq-sdk-factorial
Version: 2.2.0
Summary: Factorial wrapper from BrynQ
Home-page: UNKNOWN
Author: BrynQ
Author-email: support@brynq.com
License: BrynQ License
Platform: UNKNOWN
